[
    {"name": "astro", "email": "astro@dummy.com", "password": "1234567890"},
    {"name": "bruce", "email": "bruce@dummy.com", "password": "1234567890"},
    {"name": "carmine", "email": "carmine@dummy.com", "password": "1234567890"},
    {"name": "dillo", "email": "dillo@dummy.com", "password": "1234567890"},
    {"name": "ender", "email": "ender@dummy.com", "password": "1234567890"},
    {"name": "fish", "email": "fish@dummy.com", "password": "1234567890"},
    {"name": "ghost", "email": "ghost@dummy.com", "password": "1234567890"},
    {"name": "harley", "email": "harley@dummy.com", "password": "1234567890"},
    {"name": "ivy", "email": "ivy@dummy.com", "password": "1234567890"},
    {"name": "jelly", "email": "jelly@dummy.com", "password": "1234567890"},
    {"name": "kraken", "email": "kraken@dummy.com", "password": "1234567890"},
    {"name": "light", "email": "light@dummy.com", "password": "1234567890"},
    {"name": "molly", "email": "molly@dummy.com", "password": "1234567890"},
    {"name": "night", "email": "night@dummy.com", "password": "1234567890"},
    {"name": "osiris", "email": "osiris@dummy.com", "password": "1234567890"},
    {"name": "penguin", "email": "penguin@dummy.com", "password": "1234567890"},
    {"name": "quick", "email": "quick@dummy.com", "password": "1234567890"},
    {"name": "rocko", "email": "rocko@dummy.com", "password": "1234567890"},
    {"name": "sligo", "email": "sligo@dummy.com", "password": "1234567890"},
    {"name": "thorn", "email": "thorn@dummy.com", "password": "1234567890"},
    {"name": "ultra", "email": "ultra@dummy.com", "password": "1234567890"},
    {"name": "violet", "email": "violet@dummy.com", "password": "1234567890"},
    {"name": "wyvern", "email": "wyvern@dummy.com", "password": "1234567890"},
    {"name": "xur", "email": "xur@dummy.com", "password": "1234567890"},
    {"name": "ymir", "email": "ymir@dummy.com", "password": "1234567890"},
    {"name": "zephyr", "email": "zephyr@dummy.com", "password": "1234567890"}
]